Workbook

Sheet Inputs
A1: Current age | B1: 49
A2: Partner current age | B2: 44
A3: Planned retirement age | B3: 68
A4: Your expected lifespan | B4: 95
A5: Partner expected lifespan | B5: 99
A6: Current home value | B6: 700000
A7: Outstanding mortgage | B7: 500000
A8: Annual mortgage rate | B8: 0.05
A9: Years left on mortgage | B9: 25.3
A10: Current Cash/Savings | B10: 55000
A11: Stock portfolio | B11: 62000
A12: Annual salary | B12: 140000
... A19: Safe withdrawal rate | B19: 0.04
A20: Years to Retirement (calc) | B20: =B3-B1
A21: Years in Retirement (calc) | B21: =B4-B3
A22: Super growth % | B22: 0.09
A23: Super employer rate (SG%) | B23: 0.11
A24: Current Super balance | B24: 0
A25: ASFA comfortable couple annual (today) | B25: 73031
A26: Age Pension full couple annual (today) | B26: 46202
A27: Age Pension homeowner couple full assets threshold | B27: 481500

Sheet Calculations
A1: Years to Retirement | B1: =Inputs!B3-Inputs!B1
A2: Years in Retirement (you) | B2: =Inputs!B4-Inputs!B3
A3: Years in Retirement (partner) | B3: =Inputs!B5-Inputs!B3
A4: Monthly Mortgage Payment | B4: =-PMT(Inputs!B8/12,ROUND(Inputs!B9*12,0),Inputs!B7)
A5: Home Value at Retirement | B5: =FV(Inputs!B16,Inputs!B20,0,-Inputs!B6)
A6: Mortgage Balance at Retirement | B6: =IF(Inputs!B9<=Inputs!B20,0,ROUND(FV(Inputs!B8/12,Inputs!B20*12,-PMT(Inputs!B8/12,ROUND(Inputs!B9*12,0),Inputs!B7),-Inputs!B7),2))
A7: Net Home Equity at Retirement | B7: =B5-B6
A8: Current Combined Salary | B8: =Inputs!B12+Inputs!B13
A9: Current Annual Savings Contribution (from income) | B9: =(Inputs!B12+Inputs!B13)*Inputs!B14
A10: Annual Stock Contributions (from monthly) | B10: =Inputs!B15*12
A11: Total Annual Contributions | B11: =B8+B9
A12: Future Value of Current Savings | B12: =FV(Inputs!B18,Inputs!B20,0,-Inputs!B10)
A13: Future Value of Ongoing Annual Savings | B13: =FV(Inputs!B17,Inputs!B20,-B10,0)
A14: Future Value of Monthly Stock Contributions | B14: =FV(Inputs!B17/12,Inputs!B20*12,-Inputs!B15,0)
A15: Future Value of Current Stock Portfolio | B15: =FV(Inputs!B17,Inputs!B20,0,-Inputs!B11)
A16: Total Future Stock Portfolio | B16: =B13+B14
A17: Annual Super Contribution (employer SG) | B17: =(Inputs!B12+Inputs!B13)*Inputs!B23
A18: Future Value of Super (from current balance) | B18: =FV(Inputs!B22,Inputs!B20,-B16,-Inputs!B24)
A19: Total Assets at Retirement (ex home) | B19: =B12+B13+B17
A20: Total Assets at Retirement (incl home equity) | B20: =B18+B7
A21: ASFA comfortable annual at retirement (inflation adjusted) | B21: =Inputs!B25*(1+Inputs!B16)^Inputs!B20
A22: Required Retirement Corpus (Safe withdrawal) | B22: =B20/Inputs!B19
A23: Retirement Surplus/Shortfall | B23: =B19-B21
A24: Estimated Age Pension full couple annual (today) | B24: =Inputs!B26
A25: Age Pension assets threshold (homeowner couple) | B25: =Inputs!B27

Sheet Summary
A1: Retirement Model Summary (key outputs)
A2: Years to Retirement | B2: =Inputs!B20
A3: Home value at retirement | B3: =Calculations!B5
A4: Mortgage balance at retirement | B4: =Calculations!B6
A5: Net home equity at retirement | B5: =Calculations!B7
A6: Total assets (incl home) at retirement | B6: =Calculations!B19
A7: ASFA comfortable annual (inflation adjusted) | B7: =Calculations!B20
A8: Required retirement corpus (4% SWR) | B8: =Calculations!B21
A9: Retirement surplus / (shortfall) | B9: =Calculations!B22
