Workbook

Sheet Inputs
A1: Reference date (year) | B1: 2025
A2: Current age (you) | B2: 49
A3: Partner current age | B3: 46
A4: Planned retirement age | B4: 68
A5: Your expected lifespan | B5: 95
A6: Partner expected lifespan | B6: 99
A7: Current home value | B7: 700000
A8: Outstanding mortgage | B8: 500000
A9: Annual mortgage rate | B9: 0.0527
A10: Years left on mortgage | B10: 25.3
A11: Current Cash/Savings | B11: 55000
A12: Stock portfolio | B12: 62000
... A21: Safe withdrawal rate | B21: 0.04
A22: Super growth % (investment) | B22: =(9%/12) -> 0.0075
A23: Super employer rate (SG%) | B23: 0.11
A24: ASFA comfortable couple annual (today) | B24: 73031
A25: Age Pension full couple annual (today) | B25: 46202
A26: Age Pension homeowner couple asset threshold (today) | B26: 481500
A27: Age Pension income threshold (couple, annual) | B27: 8736
A28: Use income test? (1=yes,0=no) | B28: 1
A29: Years to Retirement (calc) | B29: =B4-B2 -> 19
A30: Years in Retirement (you) (calc) | B30: =B5-B4 -> 27

Sheet Projection
A1: Year | B1: You Age | C1: Partner Age | D1: Start Invest Balance (ex home) | E1: Contributions This Year | F1: Investment Growth This Year | G1: Super Balance | H1: Stock Balance | I1: Cash Balance | J1: Total Invest Balance (ex home) | K1: Home Value | L1: Mortgage Balance | M1: Net Home Equity | N1: Retired? (1=yes) | O1: Required Annual Income (ASFA, inflation adj) | P1: Estimated Age Pension (annual) | Q1: Withdrawals This Year (from invest balances) | R1: End Invest Balance (ex home)
A2: 2025 | B2: 49 | C2: 46 | D2: 172500 | E2: 48960 | F2: 6540 | G2: =308000 -> 308000 | H2: 78340 | I2: 74800 | J2: 172500 | K2: 700000 | L2: 490552.7 | M2: 209447.3 | N2: 0 | O2: 0 | P2: 0 | Q2: 0 | R2: 172500
A3: 2026 | B3: 50 | C3: 47 | D3: 231678.2 | E3: 48960 | F3: 10218.2 | G3: =(G2+26500)+(G2*Inputs!$B$22) -> 336810 | H3: 95823.8 | I3: 95392 | J3: 231678.2 | K3: 721000 | L3: 480607.53 | M3: 240392.47 | N3: 0 | O3: 0 | P3: 0 | Q3: 0 | R3: 231678.2
A4: 2027 | B4: 51 | C4: 48 | D4: 294803.16 | E4: 48960 | F4: 14164.96 | G4: =(G3+26500)+(G3*Inputs!$B$22) -> 365836.08 | H4: 114531.47 | I4: 116807.68 | J4: 294803.16 | K4: 742630 | L4: 470138.25 | M4: 272491.75 | N4: 0 | O4: 0 | P4: 0 | Q4: 0 | R4: 294803.16
A5: 2028 | B5: 52 | C5: 49 | D5: 362164.43 | E5: 48960 | F5: 18401.27 | G5: =(G4+26500)+(G4*Inputs!$B$22) -> 395079.85 | H5: 134548.67 | I5: 139079.99 | J5: 362164.43 | K5: 764908.9 | L5: 459117.24 | M5: 305791.66 | N5: 0 | O5: 0 | P5: 0 | Q5: 0 | R5: 362164.43
A6: 2029 | B6: 53 | C6: 50 | D6: 434074.26 | E6: 48960 | F6: 22949.83 | G6: =(G5+26500)+(G5*Inputs!$B$22) -> 424542.94 | H6: 155967.08 | I6: 162243.19 | J6: 434074.26 | K6: 787856.17 | L6: 447515.42 | M6: 340340.75 | N6: 0 | O6: 0 | P6: 0 | Q6: 0 | R6: 434074.26
A7: 2030 | B7: 54 | C7: 51 | D7: 510869.44 | E7: 48960 | F7: 27835.18 | G7: =(G6+26500)+(G6*Inputs!$B$22) -> 454227.02 | H7: 178884.77 | I7: 186332.91 | J7: 510869.44 | K7: 811491.86 | L7: 435302.18 | M7: 376189.67 | N7: 0 | O7: 0 | P7: 0 | Q7: 0 | R7: 510869.44
A8: 2031 | B8: 55 | C8: 52 | D8: 592913.35 | E8: 48960 | F8: 33083.91 | G8: =(G7+26500)+(G7*Inputs!$B$22) -> 484133.72 | H8: 203406.7 | I8: 211386.23 | J8: 592913.35 | K8: 835836.62 | L8: 422445.31 | M8: 413391.31 | N8: 0 | O8: 0 | P8: 0 | Q8: 0 | R8: 592913.35
A9: 2032 | B9: 56 | C9: 53 | D9: 680598.11 | E9: 48960 | F9: 38724.76 | G9: =(G8+26500)+(G8*Inputs!$B$22) -> 514264.72 | H9: 229645.17 | I9: 237441.68 | J9: 680598.11 | K9: 860911.72 | L9: 408910.88 | M9: 452000.84 | N9: 0 | O9: 0 | P9: 0 | Q9: 0 | R9: 680598.11
A10: 2033 | B10: 57 | C10: 54 | D10: 774346.95 | E10: 48960 | F10: 44788.84 | G10: =(G9+26500)+(G9*Inputs!$B$22) -> 544621.71 | H10: 257720.34 | I10: 264539.35 | J10: 774346.95 | K10: 886739.07 | L10: 394663.18 | M10: 492075.89 | N10: 0 | O10: 0 | P10: 0 | Q10: 0 | R10: 774346.95
A11: 2034 | B11: 58 | C11: 55 | D11: 874616.8 | E11: 48960 | F11: 51309.85 | G11: =(G10+26500)+(G10*Inputs!$B$22) -> 575206.37 | H11: 287760.76 | I11: 292720.92 | J11: 874616.8 | K11: 913341.24 | L11: 379664.64 | M11: 533676.61 | N11: 0 | O11: 0 | P11: 0 | Q11: 0 | R11: 874616.8
A12: 2035 | B12: 59 | C12: 56 | D12: 981901.05 | E12: 48960 | F12: 58324.25 | G12: =(G11+26500)+(G11*Inputs!$B$22) -> 606020.42 | H12: 319904.01 | I12: 322029.76 | J12: 981901.05 | K12: 940741.48 | L12: 363875.66 | M12: 576865.81 | N12: 0 | O12: 0 | P12: 0 | Q12: 0 | R12: 981901.05
A13: 2036 | B13: 60 | C13: 57 | D13: 1096732.6 | E13: 48960 | F13: 65871.53 | G13: =(G12+26500)+(G12*Inputs!$B$22) -> 637065.57 | H13: 354297.29 | I13: 352510.95 | J13: 1096732.6 | K13: 968963.72 | L13: 347254.61 | M13: 621709.11 | N13: 0 | O13: 0 | P13: 0 | Q13: 0 | R13: 1096732.6
A14: 2037 | B14: 61 | C14: 58 | D14: 1219687 | E14: 48960 | F14: 73994.44 | G14: =(G13+26500)+(G13*Inputs!$B$22) -> 668343.56 | H14: 391098.1 | I14: 384211.39 | J14: 1219687 | K14: 998032.63 | L14: 329757.63 | M14: 668275 | N14: 0 | O14: 0 | P14: 0 | Q14: 0 | R14: 1219687
... A20: 2043 | B20: 67 | C20: 64 | D20: 2166580 | E20: 48960 | F20: 137702.71 | G20: =(G19+26500)+(G19*Inputs!$B$22) -> 860999.84 | H20: 672772.28 | I20: 602890.34 | J20: 2166580 | K20: 1191703.2 | L20: 203618.54 | M20: 988084.63 | N20: 0 | O20: 0 | P20: 0 | Q20: 0 | R20: 2166580
A21: 2044 | B21: 68 | C21: 65 | D21: 2317972.2 | E21: 0 | F21: 151392.24 | G21: =(G20)+(G20*Inputs!$B$22) -> 867457.34 | H21: 719866.34 | I21: 627005.96 | J21: 2317972.2 | K21: 1227454.2 | L21: 178551.93 | M21: 1048902.3 | N21: 1 | O21: 128060.3 | P21: 0 | Q21: 128060.3 | R21: 2189911.9
A22: 2045 | B22: 69 | C22: 66 | D22: 2347659.4 | E22: 0 | F22: 157747.46 | G22: =(G21)+(G21*Inputs!$B$22) -> 873963.27 | H22: 770256.99 | I22: 518903.48 | J22: 2347659.4 | K22: 1264277.9 | L22: 152164.32 | M22: 1112113.6 | N22: 1 | O22: 131902.11 | P22: 0 | Q22: 131902.11 | R22: 2215757.3
A23: 2046 | B23: 70 | C23: 67 | D23: 2380420.2 | E23: 0 | F23: 164662.95 | G23: =(G22)+(G22*Inputs!$B$22) -> 880517.99 | H23: 824174.98 | I23: 402481.43 | J23: 2380420.2 | K23: 1302206.2 | L23: 124386.08 | M23: 1177820.1 | N23: 1 | O23: 135859.17 | P23: 0 | Q23: 135859.17 | R23: 2244561
A24: 2047 | B24: 71 | C24: 68 | D24: 2416756.9 | E24: 0 | F24: 172195.88 | G24: =(G23)+(G23*Inputs!$B$22) -> 887121.88 | H24: 881867.23 | I24: 277287.14 | J24: 2416756.9 | K24: 1341272.4 | L24: 95143.93 | M24: 1246128.5 | N24: 1 | O24: 139934.95 | P24: 0 | Q24: 139934.95 | R24: 2276822
A25: 2048 | B25: 72 | C25: 69 | D25: 2457231 | E25: 0 | F25: 180409.02 | G25: =(G24)+(G24*Inputs!$B$22) -> 893775.29 | H25: 943597.93 | I25: 142846.28 | J25: 2457231 | K25: 1381510.6 | L25: 64360.72 | M25: 1317149.9 | N25: 1 | O25: 144133 | P25: 0 | Q25: 144133 | R25: 2313098
A26: 2049 | B26: 73 | C26: 70 | D26: 2502430.6 | E26: 0 | F26: 189332.6 | G26: =(G25)+(G25*Inputs!$B$22) -> 900478.61 | H26: 1008273 | I26: 0 | J26: 2502430.6 | K26: 1422955.9 | L26: 31955.23 | M26: 1391000.7 | N26: 1 | O26: 148456.99 | P26: 0 | Q26: 148456.99 | R26: 2353973.6
A27: 2050 | B27: 74 | C27: 71 | D27: 2548634.9 | E27: 0 | F27: 194661.3 | G27: =(G26)+(G26*Inputs!$B$22) -> 907232.2 | H27: 920003.14 | I27: 0 | J27: 2548634.9 | K27: 1465644.6 | L27: 0 | M27: 1465644.6 | N27: 1 | O27: 152910.7 | P27: 0 | Q27: 152910.7 | R27: 2395724.2
A28: 2051 | B28: 75 | C28: 72 | D28: 2595997.5 | E28: 0 | F28: 200273.33 | G28: =(G27)+(G27*Inputs!$B$22) -> 914036.44 | H28: 820788.91 | I28: 0 | J28: 2595997.5 | K28: 1509613.9 | L28: 0 | M28: 1509613.9 | N28: 1 | O28: 157498.02 | P28: 0 | Q28: 157498.02 | R28: 2438499.5
A29: 2052 | B29: 76 | C29: 73 | D29: 2644698.7 | E29: 0 | F29: 206199.14 | G29: =(G28)+(G28*Inputs!$B$22) -> 920891.71 | H29: 709721.26 | I29: 0 | J29: 2644698.7 | K29: 1554902.3 | L29: 0 | M29: 1554902.3 | N29: 1 | O29: 162222.96 | P29: 0 | Q29: 162222.96 | R29: 2482475.7
A30: 2053 | B30: 77 | C30: 74 | D30: 2694948.6 | E30: 0 | F30: 212472.85 | G30: =(G29)+(G29*Inputs!$B$22) -> 927798.4 | H30: 585823.18 | I30: 0 | J30: 2694948.6 | K30: 1601549.4 | L30: 0 | M30: 1601549.4 | N30: 1 | O30: 167089.65 | P30: 0 | Q30: 167089.65 | R30: 2527858.9
A31: 2054 | B31: 78 | C31: 75 | D31: 2746991.5 | E31: 0 | F31: 219132.63 | G31: =(G30)+(G30*Inputs!$B$22) -> 934756.89 | H31: 448044.89 | I31: 0 | J31: 2746991.5 | K31: 1649595.9 | L31: 0 | M31: 1649595.9 | N31: 1 | O31: 172102.34 | P31: 0 | Q31: 172102.34 | R31: 2574889.2
A32: 2055 | B32: 79 | C32: 76 | D32: 2801110.4 | E32: 0 | F32: 226221.18 | G32: =(G31)+(G31*Inputs!$B$22) -> 941767.56 | H32: 295258.53 | I32: 0 | J32: 2801110.4 | K32: 1699083.8 | L32: 0 | M32: 1699083.8 | N32: 1 | O32: 177265.41 | P32: 0 | Q32: 177265.41 | R32: 2623845
... A55: 2078 | B55: 102 | C55: 99 | D55: 3297287.9 | E55: 0 | F55: 272253.13 | G55: =(G54)+(G54*Inputs!$B$22) -> 1118355.8 | H55: 0 | I55: 0 | J55: 3297287.9 | K55: 3353288.8 | L55: 0 | M55: 3353288.8 | N55: 1 | O55: 349848.61 | P55: 0 | Q55: 349848.61 | R55: 2947439.3

Sheet Summary
A1: Key Outputs Summary
A2: Years to Retirement | B2: =Inputs!B29 -> 19
A3: Home value at retirement (approx) | B3: =Projection!K21 -> 1227454.2
A4: Mortgage balance at retirement (approx) | B4: =Projection!L21 -> 178551.93
A5: Net home equity at retirement (approx) | B5: =Projection!M21 -> 1048902.3
A6: Total invest assets at retirement (ex home) | B6: =Projection!J21 -> 2317972.2
A7: ASFA comfortable annual (inflation adj at retirement) | B7: =Projection!O21 -> 128060.3
A8: Estimated Age Pension at retirement (annual) | B8: =Projection!P21 -> 0
A9: Required retirement corpus (4% SWR) | B9: =B7/Inputs!B19 -> 1829432.9
