Workbook

Sheet Inputs
A1: Parameter | B1: Value
A2: Current age | B2: 49
A3: Partner's current age | B3: 44
A4: Planned retirement age | B4: 68
A5: Your expected lifespan | B5: 95
A6: Partner's expected lifespan | B6: 99
A7: Current home value | B7: 700000
A8: Outstanding mortgage | B8: 500000
A9: Annual mortgage rate | B9: 0.0527
A10: Years left on mortgage | B10: 26.25
A11: Current Cash/Savings | B11: 55000
A12: Stock portfolio | B12: 62000
A13: Annual salary | B13: 140000
... A27: Age Pension (2025) | B27: 45037

Sheet Retirement Summary
A1: Metric | B1: Formula | C1: Value
A2: Monthly Mortgage Payment | B2: =PMT(Inputs!B9/12, Inputs!B10*12, -Inputs!B8)
A3: Home Value at Retirement | B3: =Inputs!B6*(1+Inputs!B17)^Inputs!B21
A4: Mortgage Balance at Retirement | B4: =FV(Inputs!B9/12, Inputs!B21*12, Inputs!B8, 0)
A5: Net Home Equity at Retirement | B5: =B2-B3
A6: Current Combined Salary | B6: =Inputs!B12+Inputs!B13
A7: Current Annual Savings Contribution | B7: =B4*Inputs!B14
A8: Future Value of Current Savings | B8: =Inputs!B11*(1+Inputs!B18)^Inputs!B21
A9: Future Value of Ongoing Savings Contributions | B9: =FV(Inputs!B18, Inputs!B21, B6, B7)
A10: Total Future Savings | B10: =B8+B9
A11: Future Value of Current Stock Portfolio | B11: =Inputs!B12*(1+Inputs!B17)^Inputs!B21
A12: Future Value of Monthly Stock Investments | B12: =FV(Inputs!B17/12, Inputs!B21*12, -Inputs!B15, -Inputs!B12)
A13: Total Future Stock Portfolio | B13: =B11+B12
A14: Superannuation Contributions | B14: =(Inputs!B12+Inputs!B13)*Inputs!B23
A15: Future Value of Superannuation | B15: =FV(Inputs!B24, Inputs!B21, B14, -Inputs!B22)
A16: Total Assets at Retirement | B16: =B5+B10+B13+B15
A17: Required Annual Income in Retirement | B17: =Inputs!B26*(1+Inputs!B17)^Inputs!B21
A18: Required Retirement Corpus | B18: =B17/Inputs!B19
A19: Retirement Surplus/Shortfall | B19: =B16-B18

Sheet Tax & Pension
A1: Year | B1: Taxable Income | C1: Income Tax | D1: Age Pension Eligibility | E1: Age Pension Amount
A2: =Inputs!B3+1 | B2: =Inputs!B12*Inputs!B14 | C2: =IF(B2<=18200,0,IF(B2<=45000,(B2-18200)*0.19,IF(B2<=120000,5092+(B2-45000)*0.325,IF(B2<=180000,29467+(B2-120000)*0.37,51667+(B2-180000)*0.45)))) | D2: =IF(B2<67500,"Yes","No") | E2: =IF(D2="Yes",Inputs!B28*(1+Inputs!B17)^1,0)
A3: =Inputs!B3+2 | B3: =Inputs!B12*Inputs!B14 | C3: =IF(B3<=18200,0,IF(B3<=45000,(B3-18200)*0.19,IF(B3<=120000,5092+(B3-45000)*0.325,IF(B3<=180000,29467+(B3-120000)*0.37,51667+(B3-180000)*0.45)))) | D3: =IF(B3<67500,"Yes","No") | E3: =IF(D3="Yes",Inputs!B28*(1+Inputs!B17)^2,0)
A4: =Inputs!B3+3 | B4: =Inputs!B12*Inputs!B14 | C4: =IF(B4<=18200,0,IF(B4<=45000,(B4-18200)*0.19,IF(B4<=120000,5092+(B4-45000)*0.325,IF(B4<=180000,29467+(B4-120000)*0.37,51667+(B4-180000)*0.45)))) | D4: =IF(B4<67500,"Yes","No") | E4: =IF(D4="Yes",Inputs!B28*(1+Inputs!B17)^3,0)
A5: =Inputs!B3+4 | B5: =Inputs!B12*Inputs!B14 | C5: =IF(B5<=18200,0,IF(B5<=45000,(B5-18200)*0.19,IF(B5<=120000,5092+(B5-45000)*0.325,IF(B5<=180000,29467+(B5-120000)*0.37,51667+(B5-180000)*0.45)))) | D5: =IF(B5<67500,"Yes","No") | E5: =IF(D5="Yes",Inputs!B28*(1+Inputs!B17)^4,0)
A6: =Inputs!B3+5 | B6: =Inputs!B12*Inputs!B14 | C6: =IF(B6<=18200,0,IF(B6<=45000,(B6-18200)*0.19,IF(B6<=120000,5092+(B6-45000)*0.325,IF(B6<=180000,29467+(B6-120000)*0.37,51667+(B6-180000)*0.45)))) | D6: =IF(B6<67500,"Yes","No") | E6: =IF(D6="Yes",Inputs!B28*(1+Inputs!B17)^5,0)
A7: =Inputs!B3+6 | B7: =Inputs!B12*Inputs!B14 | C7: =IF(B7<=18200,0,IF(B7<=45000,(B7-18200)*0.19,IF(B7<=120000,5092+(B7-45000)*0.325,IF(B7<=180000,29467+(B7-120000)*0.37,51667+(B7-180000)*0.45)))) | D7: =IF(B7<67500,"Yes","No") | E7: =IF(D7="Yes",Inputs!B28*(1+Inputs!B17)^6,0)
A8: =Inputs!B3+7 | B8: =Inputs!B12*Inputs!B14 | C8: =IF(B8<=18200,0,IF(B8<=45000,(B8-18200)*0.19,IF(B8<=120000,5092+(B8-45000)*0.325,IF(B8<=180000,29467+(B8-120000)*0.37,51667+(B8-180000)*0.45)))) | D8: =IF(B8<67500,"Yes","No") | E8: =IF(D8="Yes",Inputs!B28*(1+Inputs!B17)^7,0)
A9: =Inputs!B3+8 | B9: =Inputs!B12*Inputs!B14 | C9: =IF(B9<=18200,0,IF(B9<=45000,(B9-18200)*0.19,IF(B9<=120000,5092+(B9-45000)*0.325,IF(B9<=180000,29467+(B9-120000)*0.37,51667+(B9-180000)*0.45)))) | D9: =IF(B9<67500,"Yes","No") | E9: =IF(D9="Yes",Inputs!B28*(1+Inputs!B17)^8,0)
A10: =Inputs!B3+9 | B10: =Inputs!B12*Inputs!B14 | C10: =IF(B10<=18200,0,IF(B10<=45000,(B10-18200)*0.19,IF(B10<=120000,5092+(B10-45000)*0.325,IF(B10<=180000,29467+(B10-120000)*0.37,51667+(B10-180000)*0.45)))) | D10: =IF(B10<67500,"Yes","No") | E10: =IF(D10="Yes",Inputs!B28*(1+Inputs!B17)^9,0)
A11: =Inputs!B3+10 | B11: =Inputs!B12*Inputs!B14 | C11: =IF(B11<=18200,0,IF(B11<=45000,(B11-18200)*0.19,IF(B11<=120000,5092+(B11-45000)*0.325,IF(B11<=180000,29467+(B11-120000)*0.37,51667+(B11-180000)*0.45)))) | D11: =IF(B11<67500,"Yes","No") | E11: =IF(D11="Yes",Inputs!B28*(1+Inputs!B17)^10,0)
A12: =Inputs!B3+11 | B12: =Inputs!B12*Inputs!B14 | C12: =IF(B12<=18200,0,IF(B12<=45000,(B12-18200)*0.19,IF(B12<=120000,5092+(B12-45000)*0.325,IF(B12<=180000,29467+(B12-120000)*0.37,51667+(B12-180000)*0.45)))) | D12: =IF(B12<67500,"Yes","No") | E12: =IF(D12="Yes",Inputs!B28*(1+Inputs!B17)^11,0)
A13: =Inputs!B3+12 | B13: =Inputs!B12*Inputs!B14 | C13: =IF(B13<=18200,0,IF(B13<=45000,(B13-18200)*0.19,IF(B13<=120000,5092+(B13-45000)*0.325,IF(B13<=180000,29467+(B13-120000)*0.37,51667+(B13-180000)*0.45)))) | D13: =IF(B13<67500,"Yes","No") | E13: =IF(D13="Yes",Inputs!B28*(1+Inputs!B17)^12,0)
A14: =Inputs!B3+13 | B14: =Inputs!B12*Inputs!B14 | C14: =IF(B14<=18200,0,IF(B14<=45000,(B14-18200)*0.19,IF(B14<=120000,5092+(B14-45000)*0.325,IF(B14<=180000,29467+(B14-120000)*0.37,51667+(B14-180000)*0.45)))) | D14: =IF(B14<67500,"Yes","No") | E14: =IF(D14="Yes",Inputs!B28*(1+Inputs!B17)^13,0)
A15: =Inputs!B3+14 | B15: =Inputs!B12*Inputs!B14 | C15: =IF(B15<=18200,0,IF(B15<=45000,(B15-18200)*0.19,IF(B15<=120000,5092+(B15-45000)*0.325,IF(B15<=180000,29467+(B15-120000)*0.37,51667+(B15-180000)*0.45)))) | D15: =IF(B15<67500,"Yes","No") | E15: =IF(D15="Yes",Inputs!B28*(1+Inputs!B17)^14,0)
A16: =Inputs!B3+15 | B16: =Inputs!B12*Inputs!B14 | C16: =IF(B16<=18200,0,IF(B16<=45000,(B16-18200)*0.19,IF(B16<=120000,5092+(B16-45000)*0.325,IF(B16<=180000,29467+(B16-120000)*0.37,51667+(B16-180000)*0.45)))) | D16: =IF(B16<67500,"Yes","No") | E16: =IF(D16="Yes",Inputs!B28*(1+Inputs!B17)^15,0)
A17: =Inputs!B3+16 | B17: =Inputs!B12*Inputs!B14 | C17: =IF(B17<=18200,0,IF(B17<=45000,(B17-18200)*0.19,IF(B17<=120000,5092+(B17-45000)*0.325,IF(B17<=180000,29467+(B17-120000)*0.37,51667+(B17-180000)*0.45)))) | D17: =IF(B17<67500,"Yes","No") | E17: =IF(D17="Yes",Inputs!B28*(1+Inputs!B17)^16,0)
A18: =Inputs!B3+17 | B18: =Inputs!B12*Inputs!B14 | C18: =IF(B18<=18200,0,IF(B18<=45000,(B18-18200)*0.19,IF(B18<=120000,5092+(B18-45000)*0.325,IF(B18<=180000,29467+(B18-120000)*0.37,51667+(B18-180000)*0.45)))) | D18: =IF(B18<67500,"Yes","No") | E18: =IF(D18="Yes",Inputs!B28*(1+Inputs!B17)^17,0)
A19: =Inputs!B3+18 | B19: =Inputs!B12*Inputs!B14 | C19: =IF(B19<=18200,0,IF(B19<=45000,(B19-18200)*0.19,IF(B19<=120000,5092+(B19-45000)*0.325,IF(B19<=180000,29467+(B19-120000)*0.37,51667+(B19-180000)*0.45)))) | D19: =IF(B19<67500,"Yes","No") | E19: =IF(D19="Yes",Inputs!B28*(1+Inputs!B17)^18,0)
A20: =Inputs!B3+19 | B20: =Inputs!B12*Inputs!B14 | C20: =IF(B20<=18200,0,IF(B20<=45000,(B20-18200)*0.19,IF(B20<=120000,5092+(B20-45000)*0.325,IF(B20<=180000,29467+(B20-120000)*0.37,51667+(B20-180000)*0.45)))) | D20: =IF(B20<67500,"Yes","No") | E20: =IF(D20="Yes",Inputs!B28*(1+Inputs!B17)^19,0)
A21: =Inputs!B3+20 | B21: =Inputs!B12*Inputs!B14 | C21: =IF(B21<=18200,0,IF(B21<=45000,(B21-18200)*0.19,IF(B21<=120000,5092+(B21-45000)*0.325,IF(B21<=180000,29467+(B21-120000)*0.37,51667+(B21-180000)*0.45)))) | D21: =IF(B21<67500,"Yes","No") | E21: =IF(D21="Yes",Inputs!B28*(1+Inputs!B17)^20,0)
A22: =Inputs!B3+21 | B22: =Inputs!B12*Inputs!B14 | C22: =IF(B22<=18200,0,IF(B22<=45000,(B22-18200)*0.19,IF(B22<=120000,5092+(B22-45000)*0.325,IF(B22<=180000,29467+(B22-120000)*0.37,51667+(B22-180000)*0.45)))) | D22: =IF(B22<67500,"Yes","No") | E22: =IF(D22="Yes",Inputs!B28*(1+Inputs!B17)^21,0)
A23: =Inputs!B3+22 | B23: =Inputs!B12*Inputs!B14 | C23: =IF(B23<=18200,0,IF(B23<=45000,(B23-18200)*0.19,IF(B23<=120000,5092+(B23-45000)*0.325,IF(B23<=180000,29467+(B23-120000)*0.37,51667+(B23-180000)*0.45)))) | D23: =IF(B23<67500,"Yes","No") | E23: =IF(D23="Yes",Inputs!B28*(1+Inputs!B17)^22,0)
A24: =Inputs!B3+23 | B24: =Inputs!B12*Inputs!B14 | C24: =IF(B24<=18200,0,IF(B24<=45000,(B24-18200)*0.19,IF(B24<=120000,5092+(B24-45000)*0.325,IF(B24<=180000,29467+(B24-120000)*0.37,51667+(B24-180000)*0.45)))) | D24: =IF(B24<67500,"Yes","No") | E24: =IF(D24="Yes",Inputs!B28*(1+Inputs!B17)^23,0)
A25: =Inputs!B3+24 | B25: =Inputs!B12*Inputs!B14 | C25: =IF(B25<=18200,0,IF(B25<=45000,(B25-18200)*0.19,IF(B25<=120000,5092+(B25-45000)*0.325,IF(B25<=180000,29467+(B25-120000)*0.37,51667+(B25-180000)*0.45)))) | D25: =IF(B25<67500,"Yes","No") | E25: =IF(D25="Yes",Inputs!B28*(1+Inputs!B17)^24,0)
A26: =Inputs!B3+25 | B26: =Inputs!B12*Inputs!B14 | C26: =IF(B26<=18200,0,IF(B26<=45000,(B26-18200)*0.19,IF(B26<=120000,5092+(B26-45000)*0.325,IF(B26<=180000,29467+(B26-120000)*0.37,51667+(B26-180000)*0.45)))) | D26: =IF(B26<67500,"Yes","No") | E26: =IF(D26="Yes",Inputs!B28*(1+Inputs!B17)^25,0)
A27: =Inputs!B3+26 | B27: =Inputs!B12*Inputs!B14 | C27: =IF(B27<=18200,0,IF(B27<=45000,(B27-18200)*0.19,IF(B27<=120000,5092+(B27-45000)*0.325,IF(B27<=180000,29467+(B27-120000)*0.37,51667+(B27-180000)*0.45)))) | D27: =IF(B27<67500,"Yes","No") | E27: =IF(D27="Yes",Inputs!B28*(1+Inputs!B17)^26,0)
A28: =Inputs!B3+27 | B28: =Inputs!B12*Inputs!B14 | C28: =IF(B28<=18200,0,IF(B28<=45000,(B28-18200)*0.19,IF(B28<=120000,5092+(B28-45000)*0.325,IF(B28<=180000,29467+(B28-120000)*0.37,51667+(B28-180000)*0.45)))) | D28: =IF(B28<67500,"Yes","No") | E28: =IF(D28="Yes",Inputs!B28*(1+Inputs!B17)^27,0)
A29: =Inputs!B3+28 | B29: =Inputs!B12*Inputs!B14 | C29: =IF(B29<=18200,0,IF(B29<=45000,(B29-18200)*0.19,IF(B29<=120000,5092+(B29-45000)*0.325,IF(B29<=180000,29467+(B29-120000)*0.37,51667+(B29-180000)*0.45)))) | D29: =IF(B29<67500,"Yes","No") | E29: =IF(D29="Yes",Inputs!B28*(1+Inputs!B17)^28,0)
A30: =Inputs!B3+29 | B30: =Inputs!B12*Inputs!B14 | C30: =IF(B30<=18200,0,IF(B30<=45000,(B30-18200)*0.19,IF(B30<=120000,5092+(B30-45000)*0.325,IF(B30<=180000,29467+(B30-120000)*0.37,51667+(B30-180000)*0.45)))) | D30: =IF(B30<67500,"Yes","No") | E30: =IF(D30="Yes",Inputs!B28*(1+Inputs!B17)^29,0)
A31: =Inputs!B3+30 | B31: =Inputs!B12*Inputs!B14 | C31: =IF(B31<=18200,0,IF(B31<=45000,(B31-18200)*0.19,IF(B31<=120000,5092+(B31-45000)*0.325,IF(B31<=180000,29467+(B31-120000)*0.37,51667+(B31-180000)*0.45)))) | D31: =IF(B31<67500,"Yes","No") | E31: =IF(D31="Yes",Inputs!B28*(1+Inputs!B17)^30,0)
A32: =Inputs!B3+31 | B32: =Inputs!B12*Inputs!B14 | C32: =IF(B32<=18200,0,IF(B32<=45000,(B32-18200)*0.19,IF(B32<=120000,5092+(B32-45000)*0.325,IF(B32<=180000,29467+(B32-120000)*0.37,51667+(B32-180000)*0.45)))) | D32: =IF(B32<67500,"Yes","No") | E32: =IF(D32="Yes",Inputs!B28*(1+Inputs!B17)^31,0)

Sheet Investment Portfolio
A1: Year | B1: ETF Value | C1: Dividend Income | D1: Rebalanced Value
A2: =Inputs!B13*(1+Inputs!B18)^1 | B2: =B2*0.04 | C2: =B2+C2
A3: =Inputs!B13*(1+Inputs!B18)^2 | B3: =B3*0.04 | C3: =B3+C3
A4: =Inputs!B13*(1+Inputs!B18)^3 | B4: =B4*0.04 | C4: =B4+C4
A5: =Inputs!B13*(1+Inputs!B18)^4 | B5: =B5*0.04 | C5: =B5+C5
A6: =Inputs!B13*(1+Inputs!B18)^5 | B6: =B6*0.04 | C6: =B6+C6
A7: =Inputs!B13*(1+Inputs!B18)^6 | B7: =B7*0.04 | C7: =B7+C7
A8: =Inputs!B13*(1+Inputs!B18)^7 | B8: =B8*0.04 | C8: =B8+C8
A9: =Inputs!B13*(1+Inputs!B18)^8 | B9: =B9*0.04 | C9: =B9+C9
A10: =Inputs!B13*(1+Inputs!B18)^9 | B10: =B10*0.04 | C10: =B10+C10
A11: =Inputs!B13*(1+Inputs!B18)^10 | B11: =B11*0.04 | C11: =B11+C11
A12: =Inputs!B13*(1+Inputs!B18)^11 | B12: =B12*0.04 | C12: =B12+C12
A13: =Inputs!B13*(1+Inputs!B18)^12 | B13: =B13*0.04 | C13: =B13+C13
A14: =Inputs!B13*(1+Inputs!B18)^13 | B14: =B14*0.04 | C14: =B14+C14
A15: =Inputs!B13*(1+Inputs!B18)^14 | B15: =B15*0.04 | C15: =B15+C15
A16: =Inputs!B13*(1+Inputs!B18)^15 | B16: =B16*0.04 | C16: =B16+C16
A17: =Inputs!B13*(1+Inputs!B18)^16 | B17: =B17*0.04 | C17: =B17+C17
A18: =Inputs!B13*(1+Inputs!B18)^17 | B18: =B18*0.04 | C18: =B18+C18
A19: =Inputs!B13*(1+Inputs!B18)^18 | B19: =B19*0.04 | C19: =B19+C19
A20: =Inputs!B13*(1+Inputs!B18)^19 | B20: =B20*0.04 | C20: =B20+C20
A21: =Inputs!B13*(1+Inputs!B18)^20 | B21: =B21*0.04 | C21: =B21+C21
A22: =Inputs!B13*(1+Inputs!B18)^21 | B22: =B22*0.04 | C22: =B22+C22
A23: =Inputs!B13*(1+Inputs!B18)^22 | B23: =B23*0.04 | C23: =B23+C23
A24: =Inputs!B13*(1+Inputs!B18)^23 | B24: =B24*0.04 | C24: =B24+C24
A25: =Inputs!B13*(1+Inputs!B18)^24 | B25: =B25*0.04 | C25: =B25+C25
A26: =Inputs!B13*(1+Inputs!B18)^25 | B26: =B26*0.04 | C26: =B26+C26
A27: =Inputs!B13*(1+Inputs!B18)^26 | B27: =B27*0.04 | C27: =B27+C27
A28: =Inputs!B13*(1+Inputs!B18)^27 | B28: =B28*0.04 | C28: =B28+C28
A29: =Inputs!B13*(1+Inputs!B18)^28 | B29: =B29*0.04 | C29: =B29+C29
A30: =Inputs!B13*(1+Inputs!B18)^29 | B30: =B30*0.04 | C30: =B30+C30
A31: =Inputs!B13*(1+Inputs!B18)^30 | B31: =B31*0.04 | C31: =B31+C31
A32: =Inputs!B13*(1+Inputs!B18)^31 | B32: =B32*0.04 | C32: =B32+C32
